{
  "step": "STEP5_SEARCH_INDEX_CACHE_INVALIDATION",
  "generated_at": "2026-06-27 01:43:18",
  "files_checked": [
    "00_Config.gs",
    "01_Schema.gs",
    "02_Utils.gs",
    "03_DbAccess.gs",
    "04_MasterRepository.gs",
    "05_CustomerService.gs",
    "06_ContactHistoryService.gs",
    "07_NoticeService.gs",
    "08_TodayService.gs",
    "09_SupportRequestService.gs",
    "10_DashboardService.gs",
    "11_MailBridgeService.gs",
    "12_SetupDiagnostics.gs",
    "13_SettingsService.gs",
    "14_FavoriteService.gs",
    "15_PermissionService.gs",
    "16_ContractCompleteService.gs",
    "17_ActivityLogService.gs",
    "18_ConcurrencySyncService.gs",
    "19_RequestGuardService.gs",
    "20_SystemHealthService.gs",
    "21_ChangeQueueService.gs",
    "Client_Router.html",
    "Client_State.html",
    "Client_Utils.html",
    "Code.gs",
    "Component_ActivityLog.html",
    "Component_ContractComplete.html",
    "Component_CustomerDetail.html",
    "Component_CustomerSearch.html",
    "Component_Favorites.html",
    "Component_Home.html",
    "Component_Modals.html",
    "Component_Notice.html",
    "Component_Send.html",
    "Component_Support.html",
    "Component_SystemHealth.html",
    "Component_Today.html",
    "Index.html",
    "PortalMailWorkerFallbackConfig.gs",
    "Styles.html"
  ],
  "syntax": {
    "00_Config.gs": {
      "ok": true,
      "stderr": ""
    },
    "01_Schema.gs": {
      "ok": true,
      "stderr": ""
    },
    "02_Utils.gs": {
      "ok": true,
      "stderr": ""
    },
    "03_DbAccess.gs": {
      "ok": true,
      "stderr": ""
    },
    "04_MasterRepository.gs": {
      "ok": true,
      "stderr": ""
    },
    "05_CustomerService.gs": {
      "ok": true,
      "stderr": ""
    },
    "06_ContactHistoryService.gs": {
      "ok": true,
      "stderr": ""
    },
    "07_NoticeService.gs": {
      "ok": true,
      "stderr": ""
    },
    "08_TodayService.gs": {
      "ok": true,
      "stderr": ""
    },
    "09_SupportRequestService.gs": {
      "ok": true,
      "stderr": ""
    },
    "10_DashboardService.gs": {
      "ok": true,
      "stderr": ""
    },
    "11_MailBridgeService.gs": {
      "ok": true,
      "stderr": ""
    },
    "12_SetupDiagnostics.gs": {
      "ok": true,
      "stderr": ""
    },
    "13_SettingsService.gs": {
      "ok": true,
      "stderr": ""
    },
    "14_FavoriteService.gs": {
      "ok": true,
      "stderr": ""
    },
    "15_PermissionService.gs": {
      "ok": true,
      "stderr": ""
    },
    "16_ContractCompleteService.gs": {
      "ok": true,
      "stderr": ""
    },
    "17_ActivityLogService.gs": {
      "ok": true,
      "stderr": ""
    },
    "18_ConcurrencySyncService.gs": {
      "ok": true,
      "stderr": ""
    },
    "19_RequestGuardService.gs": {
      "ok": true,
      "stderr": ""
    },
    "20_SystemHealthService.gs": {
      "ok": true,
      "stderr": ""
    },
    "21_ChangeQueueService.gs": {
      "ok": true,
      "stderr": ""
    },
    "Client_Router.html": {
      "ok": true,
      "stderr": ""
    },
    "Client_State.html": {
      "ok": true,
      "stderr": ""
    },
    "Client_Utils.html": {
      "ok": true,
      "stderr": ""
    },
    "Code.gs": {
      "ok": true,
      "stderr": ""
    },
    "Component_ActivityLog.html": {
      "ok": true,
      "stderr": ""
    },
    "Component_ContractComplete.html": {
      "ok": true,
      "stderr": ""
    },
    "Component_CustomerDetail.html": {
      "ok": true,
      "stderr": ""
    },
    "Component_CustomerSearch.html": {
      "ok": true,
      "stderr": ""
    },
    "Component_Favorites.html": {
      "ok": true,
      "stderr": ""
    },
    "Component_Home.html": {
      "ok": true,
      "stderr": ""
    },
    "Component_Modals.html": {
      "ok": true,
      "stderr": ""
    },
    "Component_Notice.html": {
      "ok": true,
      "stderr": ""
    },
    "Component_Send.html": {
      "ok": true,
      "stderr": ""
    },
    "Component_Support.html": {
      "ok": true,
      "stderr": ""
    },
    "Component_SystemHealth.html": {
      "ok": true,
      "stderr": ""
    },
    "Component_Today.html": {
      "ok": true,
      "stderr": ""
    },
    "Index.html": {
      "ok": true,
      "skipped": "no <script> block"
    },
    "PortalMailWorkerFallbackConfig.gs": {
      "ok": true,
      "stderr": ""
    },
    "Styles.html": {
      "ok": true,
      "skipped": "no <script> block"
    }
  },
  "top_level_function_duplicates": {},
  "modified_files": [
    "Client_State.html",
    "Component_CustomerSearch.html"
  ],
  "checks": {
    "component_customer_search_has_force_queue": true,
    "component_customer_search_clears_all_page_cache_prefix": true,
    "client_state_tracks_dirty_meta": true,
    "search_request_seq_added": true
  }
}